plover_portuguese.py
plover_portuguese-0.2.2.dist-info/METADATA
plover_portuguese-0.2.2.dist-info/WHEEL
plover_portuguese-0.2.2.dist-info/entry_points.txt
plover_portuguese-0.2.2.dist-info/top_level.txt
plover_portuguese-0.2.2.dist-info/zip-safe
plover_portuguese-0.2.2.dist-info/RECORD
