Metadata-Version: 2.1
Name: plover_portuguese
Version: 0.2.2
Summary: Portuguese language system for Plover
Home-page: https://github.com/morinted/plover_portuguese
Author: Ted Morin
Author-email: morinted@gmail.com
License: GNU General Public License v2 or later (GPLv2+)
Keywords: plover plover_plugin
Classifier: Development Status :: 4 - Beta
Classifier: Environment :: Plugins
Classifier: Intended Audience :: End Users/Desktop
Classifier: License :: OSI Approved :: GNU General Public License v2 or later (GPLv2+)
Classifier: Operating System :: OS Independent
Classifier: Programming Language :: Python :: 3
Classifier: Programming Language :: Python :: 3.4
Classifier: Programming Language :: Python :: 3.5
Classifier: Programming Language :: Python :: 3.6
Requires-Dist: plover >=4.0.0.dev0
